LICENSE.txt
README.md
setup.py
essential_building_blocks/__init__.py
essential_building_blocks.egg-info/PKG-INFO
essential_building_blocks.egg-info/SOURCES.txt
essential_building_blocks.egg-info/dependency_links.txt
essential_building_blocks.egg-info/top_level.txt
essential_building_blocks/data_structures/__init__.py
essential_building_blocks/data_structures/common/__init__.py
essential_building_blocks/data_structures/common/data_types.py
essential_building_blocks/data_structures/lists/__init__.py
essential_building_blocks/data_structures/lists/lists.py
essential_building_blocks/mathematics/__init__.py
essential_building_blocks/mathematics/linear_algebra.py
tests/test_lists.py