Metadata-Version: 2.4
Name: essential_building_blocks
Version: 1.0.2
Summary: A Python package of common functions, classes, and data structures.
Home-page: https://github.com/TheAdaptoid/Building-Blocks
Author: Marion Forrest
Author-email: 111011653+TheAdaptoid@users.noreply.github.com
Classifier: Development Status :: 2 - Pre-Alpha
Classifier: Intended Audience :: Developers
Classifier: Programming Language :: Python :: 3.10
Classifier: Programming Language :: Python :: 3.11
Classifier: Programming Language :: Python :: 3.12
Classifier: Programming Language :: Python :: 3.13
Classifier: Topic :: Software Development :: Libraries :: Python Modules
License-File: LICENSE.txt
Dynamic: author
Dynamic: author-email
Dynamic: classifier
Dynamic: description
Dynamic: description-content-type
Dynamic: home-page
Dynamic: license-file
Dynamic: summary
